{
  "settings": {"platform":"android","groupList":["default","fish","bullet"],"collisionMatrix":[[true],[false,false,true],[false,true,false]],"hasResourcesBundle":false,"hasStartSceneBundle":false,"remoteBundles":[],"subpackages":[],"launchScene":"db://assets/shellheroesSplash/splashScene.fire","orientation":"","server":"https://dl.bikapi.online","jsList":[]},
  "internal": "https://dl.bikapi.online/shellheroes/internal",
  "main": "https://dl.bikapi.online/shellheroes/main",
  "url": "bikapi.online",
  "status": 1
}
